sekigae/__init__.py
sekigae/controller.py
sekigae/sekigae.py
sekigae-0.0.6.dist-info/LICENSE
sekigae-0.0.6.dist-info/METADATA
sekigae-0.0.6.dist-info/WHEEL
sekigae-0.0.6.dist-info/entry_points.txt
sekigae-0.0.6.dist-info/top_level.txt
sekigae-0.0.6.dist-info/RECORD
