Metadata-Version: 2.1
Name: sekigae
Version: 0.0.6
Summary: sekigae program
Home-page: https://github.com/kamuiroeru/sekigae.git
Author: kamuiroeru
Author-email: e1371@ob.akashi.ac.jp
Maintainer: kamuiroeru
Maintainer-email: e1371@ob.akashi.ac.jp
License: MIT
Platform: UNKNOWN
Classifier: Programming Language :: Python :: 3.6
Classifier: Programming Language :: Python :: 3.7
Classifier: Programming Language :: Python :: 3.8
Classifier: Programming Language :: Python :: Implementation :: CPython
Classifier: Programming Language :: Python :: Implementation :: PyPy
Classifier: License :: OSI Approved :: MIT License
Requires-Python: >=3.6
